garatool/__init__.py
garatool/__main__.py
garatool/garatool.py
garatool-0.1683950588.0.dist-info/METADATA
garatool-0.1683950588.0.dist-info/WHEEL
garatool-0.1683950588.0.dist-info/top_level.txt
garatool-0.1683950588.0.dist-info/RECORD
