Metadata-Version: 2.1
Name: garatool
Version: 0.1683950588.0
Summary: GaraSTEM Production Library
Home-page: https://github.com/curlyz/garatool
Download-URL: https://pypi.org/project/garatool/
Author: Curly Nguyen
Author-email: curly.saigonese@gmail.com
License: MIT
Keywords: GaraSTEM
Requires-Dist: termcolor
Requires-Dist: requests
Requires-Dist: msgpack
Requires-Dist: esptool
Requires-Dist: dacite
Requires-Dist: colorama
